tyora/__init__.py
tyora/__main__.py
tyora/session.py
tyora/tyora.py
tyora-0.1.0.dist-info/METADATA
tyora-0.1.0.dist-info/WHEEL
tyora-0.1.0.dist-info/entry_points.txt
tyora-0.1.0.dist-info/licenses/LICENSE
tyora-0.1.0.dist-info/RECORD
