Metadata-Version: 2.3
Name: tyora
Version: 0.1.0
Summary: CLI to interact with the mooc.fi instance of CSES
Project-URL: Homepage, https://github.com/madeddie/tyora/
Author-email: Edwin Hermans <edwin@madtech.cx>
License-Expression: MIT
License-File: LICENSE
Keywords: cli,cses,data structures and algorithms,dsa,mooc.fi,tira.mooc.fi
Classifier: Development Status :: 3 - Alpha
Classifier: Environment :: Console
Classifier: License :: OSI Approved :: MIT License
Classifier: Operating System :: OS Independent
Classifier: Programming Language :: Python
Classifier: Programming Language :: Python :: 3
Classifier: Programming Language :: Python :: 3.9
Classifier: Programming Language :: Python :: 3.10
Classifier: Programming Language :: Python :: 3.11
Classifier: Programming Language :: Python :: 3.12
Classifier: Topic :: Utilities
Classifier: Typing :: Typed
Requires-Python: >=3.9
Requires-Dist: html2text>=2024.2.26
Requires-Dist: html5lib>=1.1
Requires-Dist: platformdirs>=4.2.2
Requires-Dist: requests-toolbelt>=1.0.0
Requires-Dist: requests>=2.32.1
